[
  {
    "title": "AMD端侧AI再出新兵：RyzenClaw与RadeonClaw瞄准本地智能代理",
    "summary": "AMD推出RyzenClaw与RadeonClaw，让AI代理在本地CPU与GPU上协同运行，瞄准AI PC与边缘智能场景，强化端侧算力与隐私优势。",
    "content": "<p>在AI代理逐渐从云端走向个人设备的节点上，算力如何下沉到终端，成为产业竞逐的新焦点。</p><h3>RyzenClaw与RadeonClaw是什么？</h3><p>AMD近期发布了两项围绕本地AI代理运行的新方案——<strong>RyzenClaw</strong>与<strong>RadeonClaw</strong>。前者主要面向搭载锐龙处理器的终端设备，后者则聚焦独立显卡与数据中心级GPU，目标是在<strong>本地硬件上高效运行AI代理</strong>，而不是完全依赖云端推理。</p><p>按照AMD的规划，RyzenClaw更多对应<strong>个人电脑、掌机、边缘设备</strong>等场景，强调低功耗和响应速度；RadeonClaw则立足于<strong>高性能GPU集群</strong>与工作站，面向更复杂的多代理协同与大模型推理任务。两者在软件栈和调度机制上互相兼容，形成统一的AI运行环境。</p><h3>核心功能：从“能跑AI”到“能跑AI代理”</h3><p>与传统的AI推理方案相比，RyzenClaw和RadeonClaw更强调<strong>“AI代理（AI Agents）级别的工作流”</strong>，不仅仅是调用单个模型，而是让多个模型在本地协作、规划并执行任务。其核心能力主要集中在以下几个方面：</p><ul><li><strong>本地代理编排</strong>：支持将任务拆解为多个步骤，由不同模型（如语言模型、视觉模型、推荐模型等）在本地协同完成，减少频繁访问云端的需求。</li><li><strong>CPU、GPU、NPU一体调度</strong>：RyzenClaw针对锐龙处理器内置的CPU与NPU进行优化，而RadeonClaw聚焦GPU加速，两者通过统一的软件接口，把终端中的算力单元视作一个整体资源池。</li><li><strong>模型多格式支持</strong>：面向当前主流的开源与闭源模型生态，提供对多种权重格式与量化方案的兼容，便于开发者将现有模型迁移到本地运行。</li><li><strong>对话式与任务型代理并重</strong>：既支持类似个人助理的自然语言对话代理，也能运行面向自动化运维、内容生成、数据整理等更复杂任务型代理。</li><li><strong>隐私与离线可用</strong>：通过在本地完成推理与状态保存，可在网络不稳定或敏感数据不宜上传云端的场景下保持可用，增强数据安全性。</li></ul><h3>技术亮点：针对端侧与GPU的双栈优化</h3><p>在技术实现层面，RyzenClaw与RadeonClaw的设计核心，是让AI代理对底层硬件“感知更少、利用更好”。AMD在几个关键方向上进行了深度优化：</p><ul><li><strong>计算图与任务图融合调度</strong>：在传统模型推理的计算图基础上，增加了<strong>任务图</strong>的概念，把代理级别的规划与调用抽象为可调度节点，从而在硬件层面更好地重用中间结果与内存。</li><li><strong>针对锐龙APU的本地优化</strong>：在RyzenClaw上，AMD利用锐龙处理器<strong>CPU+集成GPU+NPU</strong>的异构结构，为不同类型算子分配最合适的执行单元，例如矩阵乘法由GPU/NPU处理、逻辑与控制流由CPU负责。</li><li><strong>为Radeon GPU提供代理级加速库</strong>：RadeonClaw针对Radeon GPU和数据中心级GPU，提供了专门的<strong>AI代理执行库</strong>，在多模型并行、上下文复用、KV缓存管理等方面进行底层优化，提高大模型长对话、多会话场景的吞吐。</li><li><strong>能耗与时延平衡</strong>：面向笔记本、掌机等移动终端，RyzenClaw引入基于场景的调度策略，在响应速度与功耗之间做动态权衡，例如短回答优先NPU执行，长任务再调度至GPU。</li><li><strong>统一开发接口</strong>：通过适配主流AI框架和推理引擎（如ONNX、部分开源推理Runtime等），为开发者提供相对统一的API，降低针对不同硬件重复优化的门槛。</li></ul><h3>对开发者与用户意味着什么？</h3><p>对于开发者而言，RyzenClaw与RadeonClaw进一步明确了<strong>“在AMD硬件上跑AI代理”的路径</strong>，从单一模型推理扩展到完整任务流执行：</p><ul><li>应用开发者可以基于这些组件，构建<strong>本地知识助手、智能桌面助手、自动化脚本代理</strong>等产品，而不必完全依赖云端API。</li><li>企业与政务机构可在<strong>内网环境</strong>部署AI代理，结合自有数据构建本地智能助手，有助于满足合规与数据主权要求。</li><li>游戏与内容创作领域，可以尝试在终端设备中引入<strong>实时AI NPC、动态剧情生成、个性化内容生成</strong>等功能，利用GPU与NPU协同提升实时性。</li></ul><p>对普通用户而言，这类端侧AI方案的普及意味着：</p><ul><li><strong>体验更即时</strong>：大量智能交互可以在本地完成，降低了延迟，对网速依赖更小。</li><li><strong>隐私保护更强</strong>：个人文档、聊天记录、图片等敏感数据可在本地进行分析与总结，减少上传云端的必要性。</li><li><strong>终端价值提升</strong>：PC、掌机、工作站等设备的硬件性能将通过AI代理“长期激活”，不再只是运行传统软件，而是成为持续进化的智能节点。</li></ul><h3>与产业趋势的呼应：AI PC与边缘智能加速落地</h3><p>从产业趋势看，全球头部厂商正在围绕<strong>AI PC、边缘AI、个人大模型</strong>展开新一轮竞争。微软推动Copilot+ PC生态，英特尔、ARM等也在不断强化NPU与GPU的端侧推理能力。AMD推出RyzenClaw与RadeonClaw，实质上是希望在这轮趋势中构建<strong>完整的软硬件协同方案</strong>。</p><p>对于中国市场，端侧AI有望在<strong>政企办公、安全可控、工业现场、智慧城市终端</strong>等多个领域发挥作用。本地运行AI代理不仅有助于降低持续使用成本，也更利于在合规及数据保护框架下，开展面向行业的定制化创新。</p><p>随着更多本地大模型与行业模型在AMD平台适配和优化，RyzenClaw与RadeonClaw有机会成为连接<strong>硬件算力、模型能力与应用场景</strong>之间的重要桥梁，加速端侧智能在真实业务中的落地。</p>",
    "link": "http://127.0.0.1:1212/pages/blog/View.html?id=1773612028",
    "path": "blog/View.html?id=1773612028",
    "id": "1773612028",
    "date": "2026年3月16日"
  },
  {
    "title": "俄罗斯公布16核/32核CPU参数：基于MIPS架构，获中国龙芯授权",
    "summary": "俄罗斯公布自研16核/32核CPU规格，基于获得中国龙芯MIPS指令集授权，引发对中俄在自主可控芯片与信息安全领域合作前景的关注。",
    "content": "<p>在欧美持续强化对高端芯片出口管制的背景下，俄罗斯正式公布新一代16核与32核桌面/服务器级CPU的关键规格，背后指令集技术来自中国龙芯授权的MIPS架构，自主可控与去“西方依赖”成为此次发布的核心信号。</p><h3>核心参数：16核/32核配置公开</h3><p>根据公开信息，这一系列处理器面向桌面与服务器场景，采用多核对称设计，重点型号包括：</p><ul><li><strong>16核型号</strong>：定位中高端桌面与入门级服务器，支持多线程与基础虚拟化能力。</li><li><strong>32核型号</strong>：面向数据中心与政府、科研等高并发场景，强调吞吐与并行处理性能。</li><li><strong>主频与功耗</strong>：官方披露其目标是在保持较高主频的同时控制功耗至可接受水平，以替代现有基于西方平台的方案。</li><li><strong>多通道内存支持</strong>：支持多通道DDR内存，为虚拟化与数据库等内存密集型负载提供保障。</li><li><strong>接口与扩展</strong>：提供常规高速I/O与扩展总线，以满足服务器板卡生态构建需要。</li></ul><p>从定位看，新CPU并未直接对标最新一代顶级x86处理器，而是强调“可用、可控、可量产”，优先满足本国政企、工业控制与信息基础设施的替代需求。</p><h3>中国龙芯MIPS授权：关键技术来源</h3><p>值得关注的是，该系列CPU采用的指令集来自中国龙芯对俄罗斯机构的授权，属于基于<strong>MIPS架构</strong>的方案。</p><ul><li><strong>指令集授权而非整机复制</strong>：俄方在取得MIPS指令集与相关IP授权后，自主完成微架构设计与SoC实现，既避免了西方专利体系的直接约束，又保留一定本土创新空间。</li><li><strong>龙芯早期技术路线的延伸</strong>：龙芯在转向自研LoongArch之前长期深耕MIPS体系，此次授权可视为其早期技术积累在海外的一次“延长服役”。</li><li><strong>规避制裁与合规路径</strong>：相较依赖美国为核心的x86、ARM授权体系，基于中方授权的MIPS路线，可在一定程度上降低被“卡脖子”的法律与供应链风险。</li></ul><p>这一合作表明，在指令集与架构层面，中国已经具备向其他国家输出成熟处理器技术能力，也使中俄在信息技术自主化上的协作进一步走向实质化。</p><h3>技术特点：成熟架构+追求稳定可控</h3><p>从技术路径来看，这一CPU系列并不追逐最新工艺与极限性能，而是突出“成熟、稳定、可部署”的工程思路。</p><ul><li><strong>成熟工艺节点</strong>：在当前制裁环境下，俄罗斯更易获得的仍是中高端而非最先进制程，成熟工艺虽然在能效与密度上不占优势，却有利于提高良率与可靠性。</li><li><strong>MIPS指令集优势</strong>：MIPS架构指令集简洁、实现难度较低，适合在本土EDA、制造能力有限的前提下快速推出可用产品。</li><li><strong>偏重通用与嵌入式混合场景</strong>：这批CPU既可部署在通用服务器、政务终端，也可延伸至工业控制、通信设备等领域，为俄方构建“非x86、非ARM”的独立生态留下空间。</li></ul><p>整体而言，该平台性能短期难以与国际顶级处理器一争高下，但在满足本国需求、自主掌控软硬件栈方面具有现实意义。</p><h3>对中俄科技合作与信息安全的影响</h3><p>此次俄罗斯CPU项目背后折射出的是中俄在信息基础设施与技术安全上的深度协同，对中国与全球半导体格局均具有多重影响。</p><ul><li><strong>中国技术输出角色增强</strong>：龙芯的指令集与相关技术经授权输出，为中国从“引进技术”向“对外授权与标准输出”转变提供了生动案例。</li><li><strong>中俄信息安全合作加深</strong>：在欧美技术封锁加剧的形势下，双方在指令集、操作系统、中间件、应用软件领域的协同空间进一步扩大，有利于构建不依赖西方核心IP的共同技术底座。</li><li><strong>推动多元化处理器生态</strong>：x86、ARM长期占据主导，本次MIPS路线的实装落地，配合中国的龙芯、飞腾、鲲鹏以及RISC-V等方案，有助于全球处理器生态走向多元。</li><li><strong>产业链安全示范效应</strong>：对包括中国在内的其他新兴市场而言，“以自有或友好指令集为基础，配合本地化软件栈”的路径，正在被俄罗斯验证为现实可行的备选方案。</li></ul><h3>中国视角：机遇与边界并存</h3><p>从中国自身利益与长期布局来看，这一事件既是机遇，也是对产业策略与合规边界的考验。</p><ul><li><strong>机遇：提升国际话语权</strong>：通过对外授权与合作，中国在处理器架构、软硬件生态中的话语权将进一步提升，有助于推动自主指令集与国产平台被更多国家采纳。</li><li><strong>生态协同空间</strong>：未来在<strong>编译器、操作系统、数据库、中间件</strong>等层面，中俄有望展开更深合作，为双方企业带来定制化、规模化的市场机遇。</li><li><strong>合规与风险把控</strong>：在复杂的国际环境下，对外技术合作须严格遵守联合国以及中国自身的出口管制和合规框架，防范因第三国制裁传导带来的连带风险。</li><li><strong>对国产产业链的启示</strong>：俄罗斯选择在制裁压力下快速走向“可用优先”的自主路线，对中国在某些关键领域加快国产化替代、避免过度依赖单一体系具有现实借鉴意义。</li></ul><h3>展望：性能不是唯一指标，自主可控价值凸显</h3><p>从技术曲线来看，这一俄罗斯自研CPU系列短期内难以改变全球算力格局，但其象征意义与示范效应不容忽视：在地缘政治与技术封锁交织的大环境下，<strong>性能不再是唯一衡量标准，自主可控、安全可靠与供应连续性正在成为重要权衡维度</strong>。</p><p>对中国而言，如何在坚持自主创新、完善国产生态的同时，稳妥推进与包括俄罗斯在内的伙伴国家的技术合作，既把握产业机遇，又守住安全与合规底线，将是未来几年半导体与信息技术战略布局中的关键课题。</p>",
    "link": "http://127.0.0.1:1212/pages/blog/View.html?id=1773633653",
    "path": "blog/View.html?id=1773633653",
    "id": "1773633653",
    "date": "2026年3月16日"
  }
]